mpdistil/__init__.py
mpdistil/__version__.py
mpdistil/config.py
mpdistil/core.py
mpdistil/curriculum.py
mpdistil/data_utils.py
mpdistil/metrics.py
mpdistil/models.py
mpdistil/trainer.py
mpdistil-0.1.0.dist-info/licenses/LICENSE
mpdistil-0.1.0.dist-info/METADATA
mpdistil-0.1.0.dist-info/WHEEL
mpdistil-0.1.0.dist-info/top_level.txt
mpdistil-0.1.0.dist-info/RECORD
