Metadata-Version: 2.4
Name: mpdistil
Version: 0.1.0
Summary: Meta-Policy Knowledge Distillation for compact student models
Home-page: https://github.com/parmanu-lcs2/mpdistil/
Author: Parmanu, LCS2, IIT Delhi
Author-email: 
License: MIT
Project-URL: Homepage, https://github.com/parmanu-lcs2/mpdistil
Project-URL: Repository, https://github.com/parmanu-lcs2/mpdistil
Keywords: knowledge-distillation,meta-learning,deep-learning,nlp,transformers
Classifier: Development Status :: 3 - Alpha
Classifier: Intended Audience :: Science/Research
Classifier: Topic :: Scientific/Engineering :: Artificial Intelligence
Classifier: License :: OSI Approved :: MIT License
Classifier: Programming Language :: Python :: 3
Requires-Python: >=3.8
License-File: LICENSE
Requires-Dist: torch>=1.13.0
Requires-Dist: transformers>=4.28.0
Requires-Dist: datasets>=2.12.0
Requires-Dist: numpy>=1.21.0
Requires-Dist: pandas>=1.3.0
Requires-Dist: scikit-learn>=1.0.0
Requires-Dist: scipy>=1.7.0
Requires-Dist: tqdm>=4.64.0
Requires-Dist: wandb>=0.15.0
Requires-Dist: matplotlib>=3.5.0
Dynamic: home-page
Dynamic: license-file
Dynamic: requires-python
